[
 {
  "default_value": null,
  "doc_type": "KPIs",
  "docstatus": 0,
  "doctype": "Property Setter",
  "doctype_or_field": "DocField",
  "field_name": "kpi_name",
  "is_system_generated": 0,
  "modified": "2025-06-18 08:58:55.525281",
  "module": null,
  "name": "KPIs-kpi_name-length",
  "property": "length",
  "property_type": "Int",
  "row_name": null,
  "value": "300"
 },
 {
  "default_value": null,
  "doc_type": "Grant",
  "docstatus": 0,
  "doctype": "Property Setter",
  "doctype_or_field": "DocField",
  "field_name": "budget_attributions_tab",
  "is_system_generated": 0,
  "modified": "2025-06-30 16:19:50.634817",
  "module": null,
  "name": "Grant-budget_attributions_tab-hidden",
  "property": "hidden",
  "property_type": "Check",
  "row_name": null,
  "value": "1"
 },
 {
  "default_value": null,
  "doc_type": "KPIs",
  "docstatus": 0,
  "doctype": "Property Setter",
  "doctype_or_field": "DocField",
  "field_name": "kpi_name",
  "is_system_generated": 1,
  "modified": "2025-07-01 17:30:56.330309",
  "module": null,
  "name": "KPIs-kpi_name-in_list_view",
  "property": "in_list_view",
  "property_type": "Check",
  "row_name": null,
  "value": "1"
 },
 {
  "default_value": null,
  "doc_type": "KPIs",
  "docstatus": 0,
  "doctype": "Property Setter",
  "doctype_or_field": "DocField",
  "field_name": "theme",
  "is_system_generated": 1,
  "modified": "2025-07-01 17:30:56.357136",
  "module": null,
  "name": "KPIs-theme-in_list_view",
  "property": "in_list_view",
  "property_type": "Check",
  "row_name": null,
  "value": "1"
 },
 {
  "default_value": null,
  "doc_type": "KPIs",
  "docstatus": 0,
  "doctype": "Property Setter",
  "doctype_or_field": "DocField",
  "field_name": "kpi_type",
  "is_system_generated": 1,
  "modified": "2025-07-01 17:30:56.362527",
  "module": null,
  "name": "KPIs-kpi_type-in_list_view",
  "property": "in_list_view",
  "property_type": "Check",
  "row_name": null,
  "value": "1"
 },
 {
  "default_value": null,
  "doc_type": "NGO",
  "docstatus": 0,
  "doctype": "Property Setter",
  "doctype_or_field": "DocField",
  "field_name": "designation",
  "is_system_generated": 0,
  "modified": "2025-07-17 15:13:07.503067",
  "module": null,
  "name": "NGO-designation-hidden",
  "property": "hidden",
  "property_type": "Check",
  "row_name": null,
  "value": "1"
 },
 {
  "default_value": null,
  "doc_type": "NGO",
  "docstatus": 0,
  "doctype": "Property Setter",
  "doctype_or_field": "DocField",
  "field_name": "signatory_designation",
  "is_system_generated": 0,
  "modified": "2025-07-17 15:15:03.478192",
  "module": null,
  "name": "NGO-signatory_designation-hidden",
  "property": "hidden",
  "property_type": "Check",
  "row_name": null,
  "value": "1"
 },
 {
  "default_value": null,
  "doc_type": "Grant",
  "docstatus": 0,
  "doctype": "Property Setter",
  "doctype_or_field": "DocField",
  "field_name": "donor",
  "is_system_generated": 0,
  "modified": "2025-04-28 12:25:39.186500",
  "module": null,
  "name": "Grant-donor-in_list_view",
  "property": "in_list_view",
  "property_type": "Check",
  "row_name": null,
  "value": "0"
 },
 {
  "default_value": null,
  "doc_type": "Grant",
  "docstatus": 0,
  "doctype": "Property Setter",
  "doctype_or_field": "DocField",
  "field_name": "donor",
  "is_system_generated": 0,
  "modified": "2025-04-28 12:25:39.302710",
  "module": null,
  "name": "Grant-donor-hidden",
  "property": "hidden",
  "property_type": "Check",
  "row_name": null,
  "value": "1"
 },
 {
  "default_value": null,
  "doc_type": "Grant",
  "docstatus": 0,
  "doctype": "Property Setter",
  "doctype_or_field": "DocField",
  "field_name": "donor",
  "is_system_generated": 0,
  "modified": "2025-04-28 12:25:39.393626",
  "module": null,
  "name": "Grant-donor-mandatory_depends_on",
  "property": "mandatory_depends_on",
  "property_type": "Data",
  "row_name": null,
  "value": ""
 },
 {
  "default_value": null,
  "doc_type": "Proposal",
  "docstatus": 0,
  "doctype": "Property Setter",
  "doctype_or_field": "DocField",
  "field_name": "input_tab",
  "is_system_generated": 0,
  "modified": "2025-05-15 16:28:48.924613",
  "module": null,
  "name": "Proposal-input_tab-label",
  "property": "label",
  "property_type": "Data",
  "row_name": null,
  "value": "Output"
 },
 {
  "default_value": null,
  "doc_type": "Proposal",
  "docstatus": 0,
  "doctype": "Property Setter",
  "doctype_or_field": "DocType",
  "field_name": null,
  "is_system_generated": 0,
  "modified": "2025-05-15 16:30:03.699184",
  "module": null,
  "name": "Proposal-main-field_order",
  "property": "field_order",
  "property_type": "Data",
  "row_name": null,
  "value": "[\"wf_state\", \"section_break_psro\", \"proposal_name\", \"project_name\", \"start_date\", \"end_date\", \"column_break_qmgi\", \"closing_date\", \"application_status\", \"grant_duration_in_months\", \"total_planned_budget\", \"reason\", \"column_break_nwys\", \"stage\", \"programme\", \"ngo\", \"vendor\", \"donor\", \"descriptive_information_section\", \"theme\", \"sdg\", \"focus_area\", \"column_break_jioh\", \"proposal_description\", \"column_break_nuci\", \"geographical_information_section\", \"column_break_shct\", \"states\", \"column_break_evjf\", \"districts\", \"demography_information_section\", \"demography_focus\", \"section_break_vkwu\", \"ngo_name\", \"ngo_poc_name\", \"ngo_email\", \"column_break_dcdx\", \"donor_name\", \"donor_poc_name\", \"donor_email\", \"column_break_nzsg\", \"grant\", \"implementation_type\", \"column_break_yqgd\", \"blocks\", \"villages\", \"column_break_qdez\", \"rfp\", \"rfp_title\", \"rfp_spoc_email\", \"draft_mou_section\", \"upload_draft_mou_here\", \"column_break_ixnh\", \"column_break_qouh\", \"section_break_vusm\", \"column_break_gmbe\", \"level_1_users\", \"level_1\", \"level_1_remarks\", \"column_break_eyco\", \"level_2_users\", \"level_2\", \"level_2_remarks\", \"column_break_ddun\", \"level_3_users\", \"level_3\", \"level_3_remarks\", \"section_break_kzjv\", \"mou_signed_column\", \"mou_signed_document\", \"mou_signing_date\", \"mou_verified\", \"tasks_tab\", \"tasks\", \"budget_tab\", \"budget\", \"tranche_tab\", \"tranche\", \"input_tab\", \"input\", \"custom_outcome_tab\", \"custom_outcome\", \"custom_impact_tab\", \"custom_impact\", \"reportings_tab\", \"reportings\", \"gallery_tab\", \"gallery\", \"amended_from\", \"email_tab\", \"email\", \"note_tab\", \"notes\", \"timeline_tab\", \"timeline\", \"additional_question_tab\", \"additional_questions\"]"
 },
 {
  "default_value": null,
  "doc_type": "Grant",
  "docstatus": 0,
  "doctype": "Property Setter",
  "doctype_or_field": "DocField",
  "field_name": "input_tab",
  "is_system_generated": 0,
  "modified": "2025-05-15 16:30:50.621925",
  "module": null,
  "name": "Grant-input_tab-label",
  "property": "label",
  "property_type": "Data",
  "row_name": null,
  "value": "Output"
 },
 {
  "default_value": null,
  "doc_type": "NGO",
  "docstatus": 0,
  "doctype": "Property Setter",
  "doctype_or_field": "DocField",
  "field_name": "applications_tab",
  "is_system_generated": 0,
  "modified": "2025-05-23 18:02:16.935276",
  "module": null,
  "name": "NGO-applications_tab-hidden",
  "property": "hidden",
  "property_type": "Check",
  "row_name": null,
  "value": "1"
 },
 {
  "default_value": null,
  "doc_type": "NGO",
  "docstatus": 0,
  "doctype": "Property Setter",
  "doctype_or_field": "DocField",
  "field_name": "section_break_nugo",
  "is_system_generated": 0,
  "modified": "2025-05-28 11:02:42.995237",
  "module": null,
  "name": "NGO-section_break_nugo-hidden",
  "property": "hidden",
  "property_type": "Check",
  "row_name": null,
  "value": "1"
 },
 {
  "default_value": null,
  "doc_type": "NGO",
  "docstatus": 0,
  "doctype": "Property Setter",
  "doctype_or_field": "DocField",
  "field_name": "routing_numbers",
  "is_system_generated": 0,
  "modified": "2025-05-28 11:02:43.078090",
  "module": null,
  "name": "NGO-routing_numbers-hidden",
  "property": "hidden",
  "property_type": "Check",
  "row_name": null,
  "value": "1"
 },
 {
  "default_value": null,
  "doc_type": "NGO",
  "docstatus": 0,
  "doctype": "Property Setter",
  "doctype_or_field": "DocField",
  "field_name": "correspondent_bank",
  "is_system_generated": 0,
  "modified": "2025-05-28 11:02:43.161468",
  "module": null,
  "name": "NGO-correspondent_bank-hidden",
  "property": "hidden",
  "property_type": "Check",
  "row_name": null,
  "value": "1"
 },
 {
  "default_value": null,
  "doc_type": "Grant",
  "docstatus": 0,
  "doctype": "Property Setter",
  "doctype_or_field": "DocField",
  "field_name": "grant_type",
  "is_system_generated": 0,
  "modified": "2025-06-02 14:15:31.144421",
  "module": null,
  "name": "Grant-grant_type-hidden",
  "property": "hidden",
  "property_type": "Check",
  "row_name": null,
  "value": "1"
 },
 {
  "default_value": null,
  "doc_type": "Grant",
  "docstatus": 0,
  "doctype": "Property Setter",
  "doctype_or_field": "DocField",
  "field_name": "funding_type",
  "is_system_generated": 0,
  "modified": "2025-06-02 14:15:31.302684",
  "module": null,
  "name": "Grant-funding_type-hidden",
  "property": "hidden",
  "property_type": "Check",
  "row_name": null,
  "value": "1"
 },
 {
  "default_value": null,
  "doc_type": "Grant",
  "docstatus": 0,
  "doctype": "Property Setter",
  "doctype_or_field": "DocField",
  "field_name": "extended_date",
  "is_system_generated": 0,
  "modified": "2025-06-02 14:15:31.408345",
  "module": null,
  "name": "Grant-extended_date-hidden",
  "property": "hidden",
  "property_type": "Check",
  "row_name": null,
  "value": "1"
 },
 {
  "default_value": null,
  "doc_type": "Proposal",
  "docstatus": 0,
  "doctype": "Property Setter",
  "doctype_or_field": "DocField",
  "field_name": "output_tab",
  "is_system_generated": 0,
  "modified": "2025-02-15 14:28:12.111689",
  "module": null,
  "name": "Proposal-output_tab-hidden",
  "property": "hidden",
  "property_type": "Check",
  "row_name": null,
  "value": "1"
 },
 {
  "default_value": null,
  "doc_type": "Proposal",
  "docstatus": 0,
  "doctype": "Property Setter",
  "doctype_or_field": "DocField",
  "field_name": "outcome_tab",
  "is_system_generated": 0,
  "modified": "2025-02-15 14:28:12.332836",
  "module": null,
  "name": "Proposal-outcome_tab-hidden",
  "property": "hidden",
  "property_type": "Check",
  "row_name": null,
  "value": "1"
 },
 {
  "default_value": null,
  "doc_type": "Proposal",
  "docstatus": 0,
  "doctype": "Property Setter",
  "doctype_or_field": "DocField",
  "field_name": "impact_tab",
  "is_system_generated": 0,
  "modified": "2025-02-15 14:28:12.468551",
  "module": null,
  "name": "Proposal-impact_tab-hidden",
  "property": "hidden",
  "property_type": "Check",
  "row_name": null,
  "value": "1"
 },
 {
  "default_value": null,
  "doc_type": "Proposal",
  "docstatus": 0,
  "doctype": "Property Setter",
  "doctype_or_field": "DocField",
  "field_name": "start_date",
  "is_system_generated": 0,
  "modified": "2025-02-15 18:50:20.091109",
  "module": null,
  "name": "Proposal-start_date-label",
  "property": "label",
  "property_type": "Data",
  "row_name": null,
  "value": "Project Start Date"
 },
 {
  "default_value": null,
  "doc_type": "Proposal",
  "docstatus": 0,
  "doctype": "Property Setter",
  "doctype_or_field": "DocField",
  "field_name": "end_date",
  "is_system_generated": 0,
  "modified": "2025-02-15 18:50:20.264373",
  "module": null,
  "name": "Proposal-end_date-label",
  "property": "label",
  "property_type": "Data",
  "row_name": null,
  "value": "Project End Date"
 },
 {
  "default_value": null,
  "doc_type": "Proposal",
  "docstatus": 0,
  "doctype": "Property Setter",
  "doctype_or_field": "DocField",
  "field_name": "grant_duration_in_months",
  "is_system_generated": 0,
  "modified": "2025-02-15 18:50:20.427991",
  "module": null,
  "name": "Proposal-grant_duration_in_months-label",
  "property": "label",
  "property_type": "Data",
  "row_name": null,
  "value": "Project Duration (in months)"
 },
 {
  "default_value": null,
  "doc_type": "Proposal",
  "docstatus": 0,
  "doctype": "Property Setter",
  "doctype_or_field": "DocField",
  "field_name": "total_planned_budget",
  "is_system_generated": 0,
  "modified": "2025-02-15 18:50:20.571087",
  "module": null,
  "name": "Proposal-total_planned_budget-label",
  "property": "label",
  "property_type": "Data",
  "row_name": null,
  "value": "Proposed Budget"
 },
 {
  "default_value": null,
  "doc_type": "Proposal",
  "docstatus": 0,
  "doctype": "Property Setter",
  "doctype_or_field": "DocField",
  "field_name": "total_planned_budget",
  "is_system_generated": 0,
  "modified": "2025-02-15 18:50:20.706429",
  "module": null,
  "name": "Proposal-total_planned_budget-description",
  "property": "description",
  "property_type": "Text",
  "row_name": null,
  "value": "This is auto-fetched from the Budget tab"
 },
 {
  "default_value": null,
  "doc_type": "Proposal",
  "docstatus": 0,
  "doctype": "Property Setter",
  "doctype_or_field": "DocField",
  "field_name": "application_status",
  "is_system_generated": 0,
  "modified": "2025-02-15 18:50:20.851031",
  "module": null,
  "name": "Proposal-application_status-label",
  "property": "label",
  "property_type": "Data",
  "row_name": null,
  "value": "Application Completion Status"
 },
 {
  "default_value": null,
  "doc_type": "Proposal",
  "docstatus": 0,
  "doctype": "Property Setter",
  "doctype_or_field": "DocField",
  "field_name": "geographical_information_section",
  "is_system_generated": 0,
  "modified": "2025-02-15 18:50:21.039542",
  "module": null,
  "name": "Proposal-geographical_information_section-collapsible",
  "property": "collapsible",
  "property_type": "Check",
  "row_name": null,
  "value": "0"
 },
 {
  "default_value": null,
  "doc_type": "Proposal",
  "docstatus": 0,
  "doctype": "Property Setter",
  "doctype_or_field": "DocField",
  "field_name": "demography_information_section",
  "is_system_generated": 0,
  "modified": "2025-02-15 18:50:21.190958",
  "module": null,
  "name": "Proposal-demography_information_section-collapsible",
  "property": "collapsible",
  "property_type": "Check",
  "row_name": null,
  "value": "0"
 },
 {
  "default_value": null,
  "doc_type": "NGO",
  "docstatus": 0,
  "doctype": "Property Setter",
  "doctype_or_field": "DocField",
  "field_name": "location_information_section",
  "is_system_generated": 0,
  "modified": "2025-02-15 19:07:11.147497",
  "module": null,
  "name": "NGO-location_information_section-collapsible",
  "property": "collapsible",
  "property_type": "Check",
  "row_name": null,
  "value": "0"
 },
 {
  "default_value": null,
  "doc_type": "NGO",
  "docstatus": 0,
  "doctype": "Property Setter",
  "doctype_or_field": "DocField",
  "field_name": "document_information_section",
  "is_system_generated": 0,
  "modified": "2025-02-15 19:07:11.278289",
  "module": null,
  "name": "NGO-document_information_section-collapsible",
  "property": "collapsible",
  "property_type": "Check",
  "row_name": null,
  "value": "0"
 },
 {
  "default_value": null,
  "doc_type": "Proposal",
  "docstatus": 0,
  "doctype": "Property Setter",
  "doctype_or_field": "DocField",
  "field_name": "proposal_description",
  "is_system_generated": 0,
  "modified": "2025-02-15 19:25:12.655723",
  "module": null,
  "name": "Proposal-proposal_description-label",
  "property": "label",
  "property_type": "Data",
  "row_name": null,
  "value": "Brief Scope of the Project"
 },
 {
  "default_value": null,
  "doc_type": "Grant",
  "docstatus": 0,
  "doctype": "Property Setter",
  "doctype_or_field": "DocType",
  "field_name": null,
  "is_system_generated": 1,
  "modified": "2024-12-23 11:10:13.913734",
  "module": null,
  "name": "Grant-main-default_print_format",
  "property": "default_print_format",
  "property_type": "Data",
  "row_name": null,
  "value": "Common Print Format"
 },
 {
  "default_value": null,
  "doc_type": "Proposal",
  "docstatus": 0,
  "doctype": "Property Setter",
  "doctype_or_field": "DocField",
  "field_name": "stage",
  "is_system_generated": 0,
  "modified": "2025-07-23 17:14:07.322747",
  "module": "mGrant - Proposal",
  "name": "Proposal-stage-options",
  "property": "options",
  "property_type": null,
  "row_name": null,
  "value": "Application Started\nProposal Submitted\nProposal Under Review\nMoU Signing ongoing\nMoU Signed\nRejected\nOn Hold"
 },
 {
  "default_value": null,
  "doc_type": "RFP",
  "docstatus": 0,
  "doctype": "Property Setter",
  "doctype_or_field": "DocField",
  "field_name": "title",
  "is_system_generated": 1,
  "modified": "2025-02-16 18:04:32.313109",
  "module": null,
  "name": "RFP-title-in_list_view",
  "property": "in_list_view",
  "property_type": "Check",
  "row_name": null,
  "value": "1"
 },
 {
  "default_value": null,
  "doc_type": "RFP",
  "docstatus": 0,
  "doctype": "Property Setter",
  "doctype_or_field": "DocField",
  "field_name": "deadline",
  "is_system_generated": 1,
  "modified": "2025-02-16 18:04:32.533874",
  "module": null,
  "name": "RFP-deadline-in_list_view",
  "property": "in_list_view",
  "property_type": "Check",
  "row_name": null,
  "value": "1"
 },
 {
  "default_value": null,
  "doc_type": "RFP",
  "docstatus": 0,
  "doctype": "Property Setter",
  "doctype_or_field": "DocField",
  "field_name": "spoc_email",
  "is_system_generated": 1,
  "modified": "2025-02-16 18:04:32.724507",
  "module": null,
  "name": "RFP-spoc_email-in_list_view",
  "property": "in_list_view",
  "property_type": "Check",
  "row_name": null,
  "value": "1"
 },
 {
  "default_value": null,
  "doc_type": "RFP",
  "docstatus": 0,
  "doctype": "Property Setter",
  "doctype_or_field": "DocField",
  "field_name": "spoc_name",
  "is_system_generated": 1,
  "modified": "2025-02-16 18:04:32.939138",
  "module": null,
  "name": "RFP-spoc_name-in_list_view",
  "property": "in_list_view",
  "property_type": "Check",
  "row_name": null,
  "value": "1"
 },
 {
  "default_value": null,
  "doc_type": "RFP",
  "docstatus": 0,
  "doctype": "Property Setter",
  "doctype_or_field": "DocField",
  "field_name": "type",
  "is_system_generated": 1,
  "modified": "2025-02-16 18:04:33.141041",
  "module": null,
  "name": "RFP-type-in_list_view",
  "property": "in_list_view",
  "property_type": "Check",
  "row_name": null,
  "value": "1"
 },
 {
  "default_value": null,
  "doc_type": "RFP",
  "docstatus": 0,
  "doctype": "Property Setter",
  "doctype_or_field": "DocField",
  "field_name": "donor",
  "is_system_generated": 1,
  "modified": "2025-02-16 18:04:31.965593",
  "module": null,
  "name": "RFP-donor-in_list_view",
  "property": "in_list_view",
  "property_type": "Check",
  "row_name": null,
  "value": "0"
 },
 {
  "default_value": null,
  "doc_type": "NGO",
  "docstatus": 0,
  "doctype": "Property Setter",
  "doctype_or_field": "DocField",
  "field_name": "state",
  "is_system_generated": 0,
  "modified": "2025-04-02 11:54:27.663310",
  "module": null,
  "name": "NGO-state-link_filter",
  "property": "link_filter",
  "property_type": null,
  "row_name": null,
  "value": "country->country"
 },
 {
  "default_value": null,
  "doc_type": "Grant",
  "docstatus": 0,
  "doctype": "Property Setter",
  "doctype_or_field": "DocField",
  "field_name": "theme",
  "is_system_generated": 0,
  "modified": "2025-07-26 16:58:14.111992",
  "module": null,
  "name": "Grant-theme-hidden",
  "property": "hidden",
  "property_type": "Check",
  "row_name": null,
  "value": "1"
 },
 {
  "default_value": null,
  "doc_type": "NGO",
  "docstatus": 0,
  "doctype": "Property Setter",
  "doctype_or_field": "DocField",
  "field_name": "project_proposal_tab",
  "is_system_generated": 0,
  "modified": "2025-07-29 17:56:56.035873",
  "module": null,
  "name": "NGO-project_proposal_tab-hidden",
  "property": "hidden",
  "property_type": "Check",
  "row_name": null,
  "value": "1"
 },
 {
  "default_value": null,
  "doc_type": "NGO",
  "docstatus": 0,
  "doctype": "Property Setter",
  "doctype_or_field": "DocField",
  "field_name": "project_tab",
  "is_system_generated": 0,
  "modified": "2025-07-29 17:56:56.126657",
  "module": null,
  "name": "NGO-project_tab-hidden",
  "property": "hidden",
  "property_type": "Check",
  "row_name": null,
  "value": "1"
 },
 {
  "default_value": null,
  "doc_type": "Grant",
  "docstatus": 0,
  "doctype": "Property Setter",
  "doctype_or_field": "DocField",
  "field_name": "frequency",
  "is_system_generated": 0,
  "modified": "2025-07-29 18:03:42.573563",
  "module": null,
  "name": "Grant-frequency-hidden",
  "property": "hidden",
  "property_type": "Check",
  "row_name": null,
  "value": "0"
 },
 {
  "default_value": null,
  "doc_type": "NGO Due Diligence",
  "docstatus": 0,
  "doctype": "Property Setter",
  "doctype_or_field": "DocField",
  "field_name": "ngo_name",
  "is_system_generated": 0,
  "modified": "2025-07-31 16:16:54.347193",
  "module": null,
  "name": "NGO Due Diligence-ngo_name-label",
  "property": "label",
  "property_type": "Data",
  "row_name": null,
  "value": "Name of Organisation"
 },
 {
  "default_value": null,
  "doc_type": "NGO",
  "docstatus": 0,
  "doctype": "Property Setter",
  "doctype_or_field": "DocField",
  "field_name": "ngo_name",
  "is_system_generated": 0,
  "modified": "2025-07-31 16:17:09.471233",
  "module": null,
  "name": "NGO-ngo_name-label",
  "property": "label",
  "property_type": "Data",
  "row_name": null,
  "value": "Name of Organisation"
 },
 {
  "default_value": null,
  "doc_type": "NGO Due Diligence",
  "docstatus": 0,
  "doctype": "Property Setter",
  "doctype_or_field": "DocField",
  "field_name": "section_break_lqqm",
  "is_system_generated": 0,
  "modified": "2025-07-31 17:31:52.774597",
  "module": null,
  "name": "NGO Due Diligence-section_break_lqqm-label",
  "property": "label",
  "property_type": "Data",
  "row_name": null,
  "value": "Organisation Information"
 },
 {
  "default_value": null,
  "doc_type": "NGO",
  "docstatus": 0,
  "doctype": "Property Setter",
  "doctype_or_field": "DocField",
  "field_name": "email",
  "is_system_generated": 0,
  "modified": "2025-07-31 17:52:48.439576",
  "module": null,
  "name": "NGO-email-label",
  "property": "label",
  "property_type": "Data",
  "row_name": null,
  "value": "E-mail"
 },
 {
  "default_value": null,
  "doc_type": "NGO Due Diligence",
  "docstatus": 0,
  "doctype": "Property Setter",
  "doctype_or_field": "DocField",
  "field_name": "contact_email",
  "is_system_generated": 0,
  "modified": "2025-07-31 17:52:59.949483",
  "module": null,
  "name": "NGO Due Diligence-contact_email-label",
  "property": "label",
  "property_type": "Data",
  "row_name": null,
  "value": "E-mail"
 },
 {
  "default_value": null,
  "doc_type": "NGO",
  "docstatus": 0,
  "doctype": "Property Setter",
  "doctype_or_field": "DocField",
  "field_name": "documents",
  "is_system_generated": 0,
  "modified": "2025-07-31 19:25:42.959248",
  "module": null,
  "name": "NGO-documents-hidden",
  "property": "hidden",
  "property_type": "Check",
  "row_name": null,
  "value": "1"
 },
 {
  "default_value": null,
  "doc_type": "NGO Due Diligence",
  "docstatus": 0,
  "doctype": "Property Setter",
  "doctype_or_field": "DocField",
  "field_name": "year_of_incorporationcommencement",
  "is_system_generated": 0,
  "modified": "2025-07-31 21:58:57.143774",
  "module": null,
  "name": "NGO Due Diligence-year_of_incorporationcommencement-label",
  "property": "label",
  "property_type": "Data",
  "row_name": null,
  "value": "Year of Establishment"
 },
 {
  "default_value": null,
  "doc_type": "NGO",
  "docstatus": 0,
  "doctype": "Property Setter",
  "doctype_or_field": "DocField",
  "field_name": "address_2",
  "is_system_generated": 0,
  "modified": "2025-07-31 22:17:37.581107",
  "module": null,
  "name": "NGO-address_2-depends_on",
  "property": "depends_on",
  "property_type": "Data",
  "row_name": null,
  "value": ""
 },
 {
  "default_value": null,
  "doc_type": "NGO",
  "docstatus": 0,
  "doctype": "Property Setter",
  "doctype_or_field": "DocField",
  "field_name": "location_information_section",
  "is_system_generated": 0,
  "modified": "2025-07-31 22:27:31.654178",
  "module": null,
  "name": "NGO-location_information_section-label",
  "property": "label",
  "property_type": "Data",
  "row_name": null,
  "value": "Organisation Registered Address"
 },
 {
  "default_value": null,
  "doc_type": "NGO",
  "docstatus": 0,
  "doctype": "Property Setter",
  "doctype_or_field": "DocField",
  "field_name": "address_1",
  "is_system_generated": 0,
  "modified": "2025-07-31 22:30:18.841548",
  "module": null,
  "name": "NGO-address_1-label",
  "property": "label",
  "property_type": "Data",
  "row_name": null,
  "value": "Address Line 1"
 },
 {
  "default_value": null,
  "doc_type": "NGO",
  "docstatus": 0,
  "doctype": "Property Setter",
  "doctype_or_field": "DocField",
  "field_name": "address_2",
  "is_system_generated": 0,
  "modified": "2025-07-31 22:30:20.312801",
  "module": null,
  "name": "NGO-address_2-label",
  "property": "label",
  "property_type": "Data",
  "row_name": null,
  "value": "Address Line 2"
 },
 {
  "default_value": null,
  "doc_type": "NGO",
  "docstatus": 0,
  "doctype": "Property Setter",
  "doctype_or_field": "DocField",
  "field_name": "contact_first_name",
  "is_system_generated": 0,
  "modified": "2025-07-31 23:06:34.806528",
  "module": null,
  "name": "NGO-contact_first_name-label",
  "property": "label",
  "property_type": "Data",
  "row_name": null,
  "value": "First Name"
 },
 {
  "default_value": null,
  "doc_type": "NGO",
  "docstatus": 0,
  "doctype": "Property Setter",
  "doctype_or_field": "DocField",
  "field_name": "contact_last_name",
  "is_system_generated": 0,
  "modified": "2025-07-31 23:06:34.952953",
  "module": null,
  "name": "NGO-contact_last_name-label",
  "property": "label",
  "property_type": "Data",
  "row_name": null,
  "value": "Last Name"
 },
 {
  "default_value": null,
  "doc_type": "NGO Due Diligence",
  "docstatus": 0,
  "doctype": "Property Setter",
  "doctype_or_field": "DocField",
  "field_name": "contact_first_name",
  "is_system_generated": 0,
  "modified": "2025-07-31 23:13:49.117500",
  "module": null,
  "name": "NGO Due Diligence-contact_first_name-label",
  "property": "label",
  "property_type": "Data",
  "row_name": null,
  "value": "First Name"
 },
 {
  "default_value": null,
  "doc_type": "NGO Due Diligence",
  "docstatus": 0,
  "doctype": "Property Setter",
  "doctype_or_field": "DocField",
  "field_name": "contact_last_name",
  "is_system_generated": 0,
  "modified": "2025-07-31 23:13:49.241756",
  "module": null,
  "name": "NGO Due Diligence-contact_last_name-label",
  "property": "label",
  "property_type": "Data",
  "row_name": null,
  "value": "Last Name"
 },
 {
  "default_value": null,
  "doc_type": "NGO",
  "docstatus": 0,
  "doctype": "Property Setter",
  "doctype_or_field": "DocField",
  "field_name": "basic_information_section",
  "is_system_generated": 0,
  "modified": "2025-07-31 23:14:58.859601",
  "module": null,
  "name": "NGO-basic_information_section-label",
  "property": "label",
  "property_type": "Data",
  "row_name": null,
  "value": "Organisation Information "
 },
 {
  "default_value": null,
  "doc_type": "NGO Due Diligence",
  "docstatus": 0,
  "doctype": "Property Setter",
  "doctype_or_field": "DocField",
  "field_name": "section_break_boov",
  "is_system_generated": 0,
  "modified": "2025-07-31 23:53:57.639618",
  "module": null,
  "name": "NGO Due Diligence-section_break_boov-label",
  "property": "label",
  "property_type": "Data",
  "row_name": null,
  "value": "Documents"
 },
 {
  "default_value": null,
  "doc_type": "NGO Due Diligence",
  "docstatus": 0,
  "doctype": "Property Setter",
  "doctype_or_field": "DocField",
  "field_name": "documents",
  "is_system_generated": 0,
  "modified": "2025-07-31 23:53:57.793226",
  "module": null,
  "name": "NGO Due Diligence-documents-label",
  "property": "label",
  "property_type": "Data",
  "row_name": null,
  "value": ""
 },
 {
  "default_value": null,
  "doc_type": "NGO Due Diligence",
  "docstatus": 0,
  "doctype": "Property Setter",
  "doctype_or_field": "DocField",
  "field_name": "key_personnel_information_section",
  "is_system_generated": 0,
  "modified": "2025-08-01 00:29:32.289180",
  "module": null,
  "name": "NGO Due Diligence-key_personnel_information_section-hidden",
  "property": "hidden",
  "property_type": "Check",
  "row_name": null,
  "value": "1"
 },
 {
  "default_value": null,
  "doc_type": "NGO Due Diligence",
  "docstatus": 0,
  "doctype": "Property Setter",
  "doctype_or_field": "DocField",
  "field_name": "upload_the_following_documents_section",
  "is_system_generated": 0,
  "modified": "2025-08-01 00:29:32.419514",
  "module": null,
  "name": "NGO Due Diligence-upload_the_following_documents_section-hidden",
  "property": "hidden",
  "property_type": "Check",
  "row_name": null,
  "value": "1"
 },
 {
  "default_value": null,
  "doc_type": "NGO Due Diligence",
  "docstatus": 0,
  "doctype": "Property Setter",
  "doctype_or_field": "DocField",
  "field_name": "section_break_ceqf",
  "is_system_generated": 0,
  "modified": "2025-08-01 00:29:32.525313",
  "module": null,
  "name": "NGO Due Diligence-section_break_ceqf-hidden",
  "property": "hidden",
  "property_type": "Check",
  "row_name": null,
  "value": "1"
 },
 {
  "default_value": null,
  "doc_type": "NGO Due Diligence",
  "docstatus": 0,
  "doctype": "Property Setter",
  "doctype_or_field": "DocField",
  "field_name": "section_break_hsly",
  "is_system_generated": 0,
  "modified": "2025-08-01 00:29:32.630183",
  "module": null,
  "name": "NGO Due Diligence-section_break_hsly-hidden",
  "property": "hidden",
  "property_type": "Check",
  "row_name": null,
  "value": "1"
 },
 {
  "default_value": null,
  "doc_type": "NGO Due Diligence",
  "docstatus": 0,
  "doctype": "Property Setter",
  "doctype_or_field": "DocField",
  "field_name": "section_break_lqxf",
  "is_system_generated": 0,
  "modified": "2025-08-01 00:29:32.732232",
  "module": null,
  "name": "NGO Due Diligence-section_break_lqxf-hidden",
  "property": "hidden",
  "property_type": "Check",
  "row_name": null,
  "value": "1"
 },
 {
  "default_value": null,
  "doc_type": "NGO Due Diligence",
  "docstatus": 0,
  "doctype": "Property Setter",
  "doctype_or_field": "DocField",
  "field_name": "section_break_pbqf",
  "is_system_generated": 0,
  "modified": "2025-08-01 00:29:32.830794",
  "module": null,
  "name": "NGO Due Diligence-section_break_pbqf-hidden",
  "property": "hidden",
  "property_type": "Check",
  "row_name": null,
  "value": "1"
 },
 {
  "default_value": null,
  "doc_type": "NGO Due Diligence",
  "docstatus": 0,
  "doctype": "Property Setter",
  "doctype_or_field": "DocField",
  "field_name": "section_break_clsy",
  "is_system_generated": 0,
  "modified": "2025-08-01 12:45:38.635804",
  "module": null,
  "name": "NGO Due Diligence-section_break_clsy-hidden",
  "property": "hidden",
  "property_type": "Check",
  "row_name": null,
  "value": "1"
 },
 {
  "default_value": null,
  "doc_type": "NGO Due Diligence",
  "docstatus": 0,
  "doctype": "Property Setter",
  "doctype_or_field": "DocField",
  "field_name": "designation",
  "is_system_generated": 0,
  "modified": "2025-08-01 16:47:30.591792",
  "module": null,
  "name": "NGO Due Diligence-designation-hidden",
  "property": "hidden",
  "property_type": "Check",
  "row_name": null,
  "value": "1"
 },
 {
  "default_value": null,
  "doc_type": "NGO",
  "docstatus": 0,
  "doctype": "Property Setter",
  "doctype_or_field": "DocType",
  "field_name": null,
  "is_system_generated": 0,
  "modified": "2025-08-01 16:50:22.761689",
  "module": null,
  "name": "NGO-main-field_order",
  "property": "field_order",
  "property_type": "Data",
  "row_name": null,
  "value": "[\"spoc_details_section\", \"email\", \"contact_first_name\", \"column_break_iqcw\", \"contact_last_name\", \"custom_telephone_s_please_mention_std_code_for_landlines\", \"contact_full_name\", \"column_break_guwq\", \"designation\", \"mobile_number\", \"custom_designations\", \"basic_information_section\", \"ngo_name\", \"custom_acronym_used_if_any\", \"custom_founder\", \"origin_type\", \"pan_number\", \"column_break_bhnv\", \"incorporated_under\", \"website\", \"primary_domain\", \"registration_of_the_organisaiton\", \"year_of_establishment\", \"column_break_qnhh\", \"focus_area\", \"ngo_status\", \"custom_ngo_size\", \"status\", \"custom_organisational_chart_\", \"custom_section_break_u4q0v\", \"custom_vision_and_mission_of_organisation\", \"custom_vision_and_mission_of_organisation_attach\", \"custom_section_break_mdtcx\", \"custom_3_major_donors_in_the_last_two_years_\", \"custom_3_major_donors_in_the_last_two_attach\", \"custom_section_break_v8xhs\", \"custom_list_of_trustees_board_of_directors_and_position\", \"custom_list_of_trustees_attach\", \"custom_section_break_712ps\", \"custom_legal_affiliation_with_another_entity_or_organisation\", \"custom_legal_affiliation_with_another_entity_attach\", \"location_information_section\", \"country\", \"pincode\", \"column_break_zjbz\", \"state\", \"stateregion\", \"address_1\", \"column_break_zlwj\", \"citytown\", \"address_2\", \"custom_section_break_qurio\", \"custom_same_as_registered_address\", \"custom_section_break_52wzi\", \"custom_country_comm\", \"custom_pincode_comm\", \"custom_column_break_ckkna\", \"custom_stateprovinceregion_comm\", \"custom_address_line_1_comm\", \"custom_column_break_bqw2n\", \"custom_citytown_comm\", \"custom_address_line_2_comm\", \"custom_section_break_bum6s\", \"district\", \"district_name\", \"column_break_pahv\", \"state_name\", \"column_break_ncbl\", \"address_3\", \"section_break_opzj\", \"is_blacklisted\", \"reason_for_blacklisting\", \"column_break_medm\", \"signatory_details_section\", \"column_break_aduo\", \"signatory_first_name\", \"signatory_last_name\", \"column_break_lizb\", \"signatory_email\", \"signatory_designation\", \"custom_signatory_designations\", \"due_diligence_section\", \"is_due_diligence_cleared\", \"is_profile_complete\", \"column_break_nsyn\", \"due_diligence_validation\", \"valid_dd\", \"column_break_qtqw\", \"reasons\", \"reason_for_due_diligence_fail\", \"bank_details_tab\", \"bank_details_section\", \"custom_column_break_gbxdc\", \"ifsc_code\", \"fetch_bank_details\", \"column_break_smhr\", \"column_break_wxpf\", \"section_break_jtzc\", \"custom_savings_current_account_number\", \"bank_name\", \"branch_name\", \"custom_column_break_raflo\", \"swift_code\", \"fcranon_fcra\", \"account_holder_name\", \"account_number\", \"custom_column_break_nnn5c\", \"correspondent_bank\", \"routing_numbers\", \"custom_section_break_z64ra\", \"bank_address\", \"column_break_txtp\", \"column_break_rmfi\", \"custom_section_break_sw4hs\", \"column_break_vpox\", \"custom_branch_address\", \"column_break_hhtv\", \"custom_column_break_svsbg\", \"section_break_pgjm\", \"bank_details_update_request\", \"documents\", \"ngo_documents\", \"section_break_nmfp\", \"renew_document\", \"column_break_iljp\", \"column_break_lsqu\", \"section_break_kyvj\", \"rejected_documents\", \"due_diligence_tab\", \"due_diligence_html\", \"section_break_ivgg\", \"countries_where_ngo_works\", \"located_countries\", \"_reasons\", \"documents_tab\", \"active_documents\", \"expired_documents\", \"work_history_tab\", \"work_references\", \"impact\", \"about_organisation\", \"files_tab\", \"files\", \"project_proposal_tab\", \"project_proposal_html\", \"project_tab\", \"project_html\", \"grants_tab\", \"grants\", \"applications_tab\", \"applications\", \"users_tab\", \"ngo_users\", \"notes_tab\", \"notes_html\", \"change_logs_tab\", \"change_logs\"]"
 },
 {
  "default_value": null,
  "doc_type": "NGO Due Diligence",
  "docstatus": 0,
  "doctype": "Property Setter",
  "doctype_or_field": "DocField",
  "field_name": "ngo_size",
  "is_system_generated": 0,
  "modified": "2025-08-01 16:50:41.063016",
  "module": null,
  "name": "NGO Due Diligence-ngo_size-fetch_from",
  "property": "fetch_from",
  "property_type": "Small Text",
  "row_name": null,
  "value": "ngo.custom_ngo_size"
 },
 {
  "default_value": null,
  "doc_type": "KPIs",
  "docstatus": 0,
  "doctype": "Property Setter",
  "doctype_or_field": "DocField",
  "field_name": "theme",
  "is_system_generated": 0,
  "modified": "2025-08-02 23:34:26.766902",
  "module": null,
  "name": "KPIs-theme-reqd",
  "property": "reqd",
  "property_type": "Check",
  "row_name": null,
  "value": "1"
 },
 {
  "default_value": null,
  "doc_type": "KPIs",
  "docstatus": 0,
  "doctype": "Property Setter",
  "doctype_or_field": "DocField",
  "field_name": "section_break_kelu",
  "is_system_generated": 0,
  "modified": "2025-08-02 23:44:19.510311",
  "module": null,
  "name": "KPIs-section_break_kelu-label",
  "property": "label",
  "property_type": "Data",
  "row_name": null,
  "value": "KPI Details"
 },
 {
  "default_value": null,
  "doc_type": "KPIs",
  "docstatus": 0,
  "doctype": "Property Setter",
  "doctype_or_field": "DocField",
  "field_name": "reporting_value_type",
  "is_system_generated": 0,
  "modified": "2025-08-02 23:44:19.600367",
  "module": null,
  "name": "KPIs-reporting_value_type-hidden",
  "property": "hidden",
  "property_type": "Check",
  "row_name": null,
  "value": "1"
 },
 {
  "default_value": null,
  "doc_type": "KPIs",
  "docstatus": 0,
  "doctype": "Property Setter",
  "doctype_or_field": "DocField",
  "field_name": "section_break_nwun",
  "is_system_generated": 0,
  "modified": "2025-08-02 23:44:19.671961",
  "module": null,
  "name": "KPIs-section_break_nwun-label",
  "property": "label",
  "property_type": "Data",
  "row_name": null,
  "value": "Focus Area Details"
 },
 {
  "default_value": null,
  "doc_type": "KPIs",
  "docstatus": 0,
  "doctype": "Property Setter",
  "doctype_or_field": "DocType",
  "field_name": null,
  "is_system_generated": 0,
  "modified": "2025-08-02 23:46:57.509765",
  "module": null,
  "name": "KPIs-main-field_order",
  "property": "field_order",
  "property_type": "Data",
  "row_name": null,
  "value": "[\"section_break_kelu\", \"kpi_type\", \"kpi_name\", \"column_break_httu\", \"unit\", \"section_break_bdgp\", \"custom_column_break_2tcyq\", \"reporting_value_type\", \"column_break_ctme\", \"column_break_xbqx\", \"section_break_nwun\", \"column_break_vjmw\", \"theme\", \"custom_pillar_\", \"column_break_vghm\", \"focus_area\", \"column_break_xnpz\", \"sdg\", \"section_break_aeup\", \"description\"]"
 },
 {
  "default_value": null,
  "doc_type": "KPIs",
  "docstatus": 0,
  "doctype": "Property Setter",
  "doctype_or_field": "DocField",
  "field_name": "unit",
  "is_system_generated": 0,
  "modified": "2025-08-02 23:48:48.238330",
  "module": null,
  "name": "KPIs-unit-label",
  "property": "label",
  "property_type": "Data",
  "row_name": null,
  "value": "Indicator Unit"
 },
 {
  "default_value": null,
  "doc_type": "Grant",
  "docstatus": 0,
  "doctype": "Property Setter",
  "doctype_or_field": "DocType",
  "field_name": null,
  "is_system_generated": 0,
  "modified": "2025-08-03 08:11:40.950000",
  "module": null,
  "name": "Grant-main-field_order",
  "property": "field_order",
  "property_type": "Data",
  "row_name": null,
  "value": "[\"details_tab\", \"sub_granting_section\", \"column_break_jbnd\", \"implementation_type\", \"column_break_htax\", \"parent_grant\", \"column_break_vssb\", \"project\", \"year\", \"year_sequence\", \"section_break_psro\", \"grant_name\", \"project_name\", \"programme\", \"ngo\", \"donor\", \"custom_entities\", \"vendor\", \"column_break_qmgi\", \"start_date\", \"end_date\", \"grant_duration_in_months\", \"other_fund_sources\", \"grant_status\", \"column_break_nwys\", \"grant_type\", \"funding_type\", \"subgranting_status\", \"grant_agreement_mou\", \"extended_date\", \"mou_signing_date\", \"descriptive_information_section\", \"theme\", \"custom_themes\", \"sdg\", \"focus_area\", \"column_break_dnll\", \"grant_description\", \"column_break_aqum\", \"geographical_information_section\", \"column_break_shct\", \"states\", \"districts\", \"column_break_evjf\", \"blocks\", \"villages\", \"column_break_syvc\", \"section_break_nbbo\", \"total_planned_budget\", \"total_amount_requested_from_donor\", \"lfas_copied\", \"column_break_judq\", \"total_funds_received\", \"total_funds_utilised\", \"column_break_jfsi\", \"total_unspent_funds\", \"section_break_vkwu\", \"demography_focus\", \"subgranting_information_section\", \"partner_ngo\", \"parnter_vendor\", \"column_break_dwqw\", \"total_funds_subgranted\", \"total_subgrant_utilisation\", \"section_break_cerd\", \"column_break_jmwk\", \"proposal\", \"column_break_pyvg\", \"column_break_rsvl\", \"section_break_zwep\", \"ngo_email\", \"geography_tab\", \"lowest_geography_level\", \"geography_html\", \"section_break_voaq\", \"geography_details\", \"timeframe_tab\", \"frequency\", \"annual_project\", \"section_break_moap\", \"quaterly_project\", \"tasks_tab\", \"section_break_sddg\", \"general_task_open\", \"column_break_bhnl\", \"general_task_in_progress\", \"column_break_vbcn\", \"general_task_delayed\", \"column_break_fobn\", \"general_task_close\", \"milestones_task_section\", \"milestones_task_open\", \"column_break_wmvu\", \"milestones_task_in_progress\", \"column_break_udaf\", \"milestones_task_delayed\", \"column_break_wawp\", \"milestones_task_close\", \"general_tasks_section\", \"tasks\", \"budget_tab\", \"budget_total_commitment_amount\", \"column_break_thym\", \"budget_total_disbursed_amount\", \"column_break_ucgw\", \"budget_total_utilised_amount\", \"column_break_zyiq\", \"budget_unutilised_disbursed_amount\", \"section_break_tdwg\", \"budget\", \"custom_budget_utilisation\", \"quarterly_utilisation\", \"financial_years\", \"budget_attributions_tab\", \"total_commitment_amount\", \"column_break_ltjm\", \"total_utilised_amount\", \"column_break_jxtf\", \"total_gap_amount\", \"section_break_hptq\", \"budget_attribution_html\", \"tranche_tab\", \"section_break_joze\", \"tranche_total_commitment_amount\", \"column_break_bnzu\", \"tranche_total_disbursed_amount\", \"column_break_vvhm\", \"tranche_total_utilised_amount\", \"column_break_vefg\", \"tranche_unutilised_disbursed_amount\", \"section_break_xkmx\", \"column_break_aekz\", \"fund_requests\", \"fund_disbursements_section\", \"fund_disbursements\", \"section_break_atad\", \"tranche\", \"input_tab\", \"input\", \"periodic_input_achievement\", \"custom_outcome_tab\", \"custom_outcome\", \"custom_periodic_outcome_achievement\", \"custom_impact_tab\", \"custom_impact\", \"custom_periodic_impact_achievement\", \"reportings_tab\", \"reportings\", \"contacts_tab\", \"contacts\", \"gallery_tab\", \"gallery\", \"amended_from\", \"email_tab\", \"custom_section_break_3vdw2\", \"email\", \"sub_grants_tab\", \"sub_grants\", \"notes_tab\", \"notes\", \"timeline_tab\", \"timeline\"]"
 },
 {
  "default_value": null,
  "doc_type": "Grant",
  "docstatus": 0,
  "doctype": "Property Setter",
  "doctype_or_field": "DocField",
  "field_name": "timeframe_tab",
  "is_system_generated": 0,
  "modified": "2025-08-04 10:53:25.906535",
  "module": null,
  "name": "Grant-timeframe_tab-hidden",
  "property": "hidden",
  "property_type": "Check",
  "row_name": null,
  "value": "1"
 },
 {
  "default_value": null,
  "doc_type": "NGO Due Diligence",
  "docstatus": 0,
  "doctype": "Property Setter",
  "doctype_or_field": "DocType",
  "field_name": null,
  "is_system_generated": 0,
  "modified": "2025-08-06 11:42:14.996111",
  "module": null,
  "name": "NGO Due Diligence-main-field_order",
  "property": "field_order",
  "property_type": "Data",
  "row_name": null,
  "value": "[\"workflow_state\", \"section_break_orth\", \"ngo\", \"column_break_zpbq\", \"origin_type\", \"column_break_erdk\", \"spoc_details_section\", \"contact_email\", \"contact_first_name\", \"column_break_duiz\", \"contact_last_name\", \"designation\", \"custom_designation2\", \"contact_full_name\", \"column_break_oyeg\", \"mobile_number\", \"custom_telephone_s_please_mention_std_code_for_landlines\", \"section_break_lqqm\", \"ngo_name\", \"custom_acronym_used_if_any\", \"custom_founder\", \"column_break_jcla\", \"registration_of_the_organisaiton\", \"website\", \"column_break_uggg\", \"ngo_size\", \"custom_organisational_chart_\", \"year_of_incorporationcommencement\", \"custom_section_break_6bbel\", \"custom_vision_and_mission_of_organisation\", \"custom_vision_and_mission_of_organisation_attach\", \"custom_section_break_0s6on\", \"custom_list_of_trustees_board_of_directors_and_position\", \"custom_list_of_trustees_board_of_directors_and_position_attach\", \"custom_section_break_vzmlp\", \"custom_legal_affiliation_with_another_entity_or\", \"custom_legal_affiliation_with_another_entity_or_attach\", \"custom_organisation_registered_address\", \"custom_country\", \"custom_pincode\", \"custom_column_break_xae0r\", \"custom_stateprovinceregion\", \"custom_address_line_1\", \"custom_column_break_afbqh\", \"custom_citytown\", \"custom_address_line_2\", \"custom_organisation_communication_address\", \"custom_country_comm\", \"custom_pincode_comm\", \"custom_column_break_rrvn7\", \"custom_stateprovinceregion_comm\", \"custom_address_line_1_comm\", \"custom_column_break_hpf9i\", \"custom_citytown_comm\", \"custom_address_line_2_comm\", \"section_break_vxkx\", \"working_countries\", \"column_break_bdko\", \"located_countries\", \"column_break_vpur\", \"annual_turnover\", \"section_break_clsy\", \"business_office_address\", \"column_break_ihro\", \"registered_office_address\", \"column_break_qscv\", \"custom_section_break_le4j3\", \"custom_column_break_kl9cn\", \"custom__trust_deed\", \"custom__trust_deed_attach\", \"custom_registration_certificate_text\", \"custom_registration_certificate_attach\", \"custom__moa__rules__reg\", \"custom__moa__rules__reg_attach\", \"custom_registration_certificate__cin_\", \"custom_registration_certificate__cin__attach\", \"custom_column_break_c5spv\", \"section_break_boov\", \"documents\", \"custom_section_break_ifuw4\", \"custom_labour_laws\", \"custom_employees_provident_fund_act_if_applicable\", \"custom_employees_provident_fund_act_attach\", \"custom_employees_state_insurance_corporation_act\", \"custom_employees_state_insurance_corporation_act_attach\", \"custom_profession_tax_if_applicable\", \"custom_profession_tax_if_applicable_attach\", \"custom_column_break_syjm2\", \"custom_section_break_l7ctt\", \"custom_income__expenditure\", \"custom_income__expenditure_balance_sheet__audit_reports_attach\", \"custom_income_tax_returns_for_the_last_3_years\", \"custom_income_tax_returns_for_the_last_3_years_attach\", \"custom_fcra_returns_for_the_last_3_years\", \"custom_fcra_returns_for_the_last_3_years_attach\", \"custom_is_there_a_process_of_internal\", \"custom_when_was_the_last_internal_audit_conducted_\", \"custom_when_was_the_last_internal_audit_conducted__attach\", \"custom_how_many_people_approve_banking_transactions\", \"custom_section_break_fs324\", \"custom_does_the_organisation\", \"custom_does_the_organisation_maintain_a_fixed__attach\", \"custom_are_there_cash_payments_made_to_vendors\", \"custom_are_employees_paid_in_cash_for_travel\", \"custom_column_break_szpei\", \"custom_are_employees_paid_in_cash_for_salary\", \"custom_does_the_organisation_\", \"custom_what_accounting_software_is_used_by_the_organisation\", \"custom_section_break_xr2yz\", \"custom_how_do_you_manage_and_monitor_programme_expenditure\", \"custom_governance\", \"custom_does_the_organisation_have_a_written_code_of_conduct\", \"custom_does_the_organisation_have_a_written_code_attach\", \"custom_does_the_organisation_have_a_written_hr_policy\", \"custom_does_the_organisation_have_a_written_attach\", \"custom_does_the_organisation_have_a_written_posh_policy\", \"custom_does_the_organisation_have_a_written_posh_policy_attach\", \"custom_does_the_organisation_have_a_written_whi\", \"custom_does_the__have_a_written_whistleblowing_attach\", \"custom_does_the_organisation_have_a_written_antifraud\", \"custom_does_the_organisation_have_a_written_anti_attach\", \"custom_does_the_organisation_have_a_written_conflict\", \"custom_does_the_organisation_have_a_written_conflict_attach\", \"custom_column_break_ttccr\", \"custom_have_there_been_any_incidents_of_noncompliance\", \"custom_does_the_organisation_have_a_written_finance_policy\", \"custom_does_the_organisation_have_a_written_finance_attach\", \"custom_does_the_organisation_have_a_written_risk\", \"custom_does_the_have_a_written_risk_register_risk_attach\", \"custom_does_the_organisation_have_a_written_procurement_policy\", \"custom_does_the_organisation_have_a_written_procurement_attach\", \"custom_does_the_organisation_have_a_written_it_and_data_\", \"custom_does_have_a_written_it_and_data_management_attach\", \"custom_are_there_any_organisation_litigations\", \"custom_are_there_any_organisation_litigations_\", \"custom_section_break_w7iuc\", \"custom_what_are_the_main_risks_for_your_organisation\", \"custom_what_trainings_are_provided_to_staff\", \"key_personnel_information_section\", \"table_fcls\", \"upload_the_following_documents_section\", \"pan\", \"pan_number\", \"date_of_issuance\", \"date_of_expiry\", \"column_break_ffky\", \"g80_certificate\", \"g80_number\", \"g80_date_of_issuance\", \"g80_date_of_expiry\", \"column_break_xtoe\", \"a12_certificate\", \"a12_number\", \"a12_date_of_issuance\", \"a12_date_of_expiry\", \"section_break_ceqf\", \"csr_1_form\", \"csr_number\", \"csr_date_of_issuance\", \"csr_date_of_expiry\", \"column_break_toef\", \"trust_deed\", \"trust_deed_number\", \"trust_deed_date_of_issuance\", \"trust_deed_date_of_expiry\", \"column_break_gbnm\", \"fcra\", \"fcra_number\", \"fcra_date_of_issuance\", \"fcra_date_of_expiry\", \"section_break_hsly\", \"gst\", \"gst_number\", \"gst_date_of_issuance\", \"gst_date_of_expiry\", \"column_break_hjmc\", \"yrs_balance_sheet\", \"balance_sheet_number\", \"balance_sheet_date_of_issuance\", \"balance_sheet_date_of_expiry\", \"column_break_xkzw\", \"yrs_annual_report\", \"annual_report_number\", \"annual_report_date_of_issuance\", \"annual_report_date_of_expiry\", \"section_break_lqxf\", \"has_code_of_conduct\", \"code_of_conduct_attachment\", \"column_break_xswl\", \"column_break_axix\", \"legal_and_regulatory_issues_section\", \"investigation_status\", \"litigation_status\", \"table_kqtm\", \"section_break_pbqf\", \"family_members_in_org\", \"table_rgtw\", \"section_break_twda\", \"due_diligence_validation\", \"status\", \"reasons\", \"reason_for_due_diligence_fail\", \"column_break_jhcn\", \"column_break_gmah\", \"hidden_fields_section\", \"amended_from\", \"created_on\", \"ngo_email\", \"custom_programmatic_details\", \"custom_programmatic_review2\", \"custom_past_programme\", \"custom_similar_programmes\", \"custom_please_enter_the_details\", \"custom_column_break_o8xfm\", \"custom_past_reports\", \"custom_attach_supporting_documents_references_1\", \"custom_section_break_h8dnh\", \"custom_team_capacity\", \"custom_qualified_staff\", \"custom_staff_attachment\", \"custom_training_measures\", \"custom_training_attachment\", \"custom_section_break_7qzd8\", \"custom_monitoring_mel\", \"custom_me_processes\", \"custom_data_collection\", \"custom_section_break_nfdv3\", \"custom_organisational_chart_for_mel_team\", \"custom_mel_exp_in_the_last_ended_fy_as_per_the_audited_inc__exp\", \"custom_column_break_dg53v\", \"custom_section_break_7urfn\", \"custom_community_engagement\", \"custom_how_does_the_organisation_engage_with_local_communities_\", \"custom_section_break_bexv8\", \"custom_government_collaboration\", \"custom_does_organisation_have_an_existing_partnership\", \"custom_please_specify_govt_collaboration_recognition\", \"custom_please_specify_govt_collaboration_recognition_attach\", \"custom_section_break_5ddp1\", \"custom_financial_controls\", \"custom_to_verify_hard_copies_against_scanned_copies_of\", \"custom_attach_supporting_documents_references_2\", \"custom_bank_reconciliation_statement__see_at_least_3_months_\", \"custom_attach_supporting_documents_references_3\", \"custom_salary_disbursement_see_at_least_3_months\", \"custom_attach_supporting_documents_references_4\", \"custom_deduction_and_deposit_of_epf_and_esi_contributions__\", \"custom_attach_supporting_documents_references_5\", \"custom_deduction_and_deposit_of_tds_at_least_3_months_\", \"custom_attach_supporting_documents_references_6\", \"custom_filing_of_form_10bd_atleast_last_fy_records_\", \"custom_attach_supporting_documents_references_7\", \"custom_sample_high_value_procurement\", \"custom_attach_supporting_documents_references_8\", \"custom_sample_board__trust_meetings_\", \"custom_attach_supporting_documents_references_9\", \"custom_safeguarding\", \"custom_safeguarding_officer\", \"custom_officer_attach\", \"custom_safeguarding_policies\", \"custom_policies_attach\", \"custom_safeguarding_training\", \"custom_training_attach_sg\", \"custom_reporting_mechanisms\", \"custom_reporting_attach\", \"custom_background_checks\", \"custom_checks_attach\", \"custom_policy_review\", \"custom_review_attach\", \"custom_whistleblowing_policy\", \"custom_whistle_attach\", \"custom_pm_recommendation\", \"custom_attach_programme_lead_review_sheet\", \"custom_selection_reasons\", \"custom_organisation_risks\", \"custom_recommendation\", \"custom_comments\", \"custom_date\", \"custom_section_break_sizgu\", \"custom_final_recommendation\", \"custom_overall_recommendation\", \"custom_column_break_muawb\"]"
 }
]